patchs_unsloth_llamacpp/__init__.py
patchs_unsloth_llamacpp/convert_hf_to_gguf.py
patchs_unsloth_llamacpp/patch.py
patchs_unsloth_llamacpp/change_file/grpo_content.py
patchs_unsloth_llamacpp/change_file/trainer_content.py
patchs_unsloth_llamacpp/change_file/unsloth_zoo_content.py
patchs_unsloth_llamacpp/gguf-py/examples/reader.py
patchs_unsloth_llamacpp/gguf-py/examples/writer.py
patchs_unsloth_llamacpp/gguf-py/gguf/__init__.py
patchs_unsloth_llamacpp/gguf-py/gguf/constants.py
patchs_unsloth_llamacpp/gguf-py/gguf/gguf.py
patchs_unsloth_llamacpp/gguf-py/gguf/gguf_reader.py
patchs_unsloth_llamacpp/gguf-py/gguf/gguf_writer.py
patchs_unsloth_llamacpp/gguf-py/gguf/lazy.py
patchs_unsloth_llamacpp/gguf-py/gguf/metadata.py
patchs_unsloth_llamacpp/gguf-py/gguf/py.typed
patchs_unsloth_llamacpp/gguf-py/gguf/quants.py
patchs_unsloth_llamacpp/gguf-py/gguf/tensor_mapping.py
patchs_unsloth_llamacpp/gguf-py/gguf/utility.py
patchs_unsloth_llamacpp/gguf-py/gguf/vocab.py
patchs_unsloth_llamacpp/gguf-py/gguf/scripts/__init__.py
patchs_unsloth_llamacpp/gguf-py/gguf/scripts/gguf_convert_endian.py
patchs_unsloth_llamacpp/gguf-py/gguf/scripts/gguf_dump.py
patchs_unsloth_llamacpp/gguf-py/gguf/scripts/gguf_hash.py
patchs_unsloth_llamacpp/gguf-py/gguf/scripts/gguf_new_metadata.py
patchs_unsloth_llamacpp/gguf-py/gguf/scripts/gguf_set_metadata.py
patchs_unsloth_llamacpp/gguf-py/tests/__init__.py
patchs_unsloth_llamacpp/gguf-py/tests/test_metadata.py
patchs_unsloth_llamacpp/gguf-py/tests/test_quants.py
patchs_unsloth_llamacpp-0.0.4.dist-info/licenses/LICENSE
patchs_unsloth_llamacpp-0.0.4.dist-info/METADATA
patchs_unsloth_llamacpp-0.0.4.dist-info/WHEEL
patchs_unsloth_llamacpp-0.0.4.dist-info/top_level.txt
patchs_unsloth_llamacpp-0.0.4.dist-info/RECORD
