Metadata-Version: 2.4
Name: patchs_unsloth_llamacpp
Version: 0.0.4
Summary: A patch to enable llama.cpp as acceleration backend on windows platform
Author-email: Linze Liu <liuzhi1999@foxmail.com>
License: 
Project-URL: Homepage, https://github.com/liuzhi19121999/patchs_unsloth_llamacpp
Project-URL: Issues, https://github.com/liuzhi19121999/patchs_unsloth_llamacpp/issues
Keywords: ai,llm,unsloth,llama
Classifier: Programming Language :: Python :: 3
Classifier: Operating System :: OS Independent
Requires-Python: <3.13,>=3.9
License-File: LICENSE
Dynamic: license-file
